{
  "type": "FeatureCollection",
  "features": [
    {
      "type": "Feature",
      "geometry": {
        "type": "Point",
        "coordinates": [
          "34.2333",
          "50.2323"
        ]
      },
      "properties": {
        "project_title": "Super project",
        "key_funding_amount": null,
        "key_funding_source": "Source",
        "id": 703,
        "project_description": null,
        "region_id": 965,
        "recipient": null,
        "lead_organization": null,
        "latitude": "50.2323",
        "longitude": "34.2333",
        "categories": [

        ],
        "scope": null,
        "planning_area": null,
        "second_planning_area": null,
        "total_project_cost": null,
        "funding_subtype": "Subtype",
        "funding_call_year": null,
        "funding_call_month": null,
        "project_status": null
      }
    }
  ]
}